pyobjectID/__init__.py
pyobjectID/errors.py
pyobjectID/generate.py
pyobjectID/object_to_string.py
pyobjectID/string_to_object.py
pyobjectID/validate.py
tests/__init__.py
tests/test_generate.py
tests/test_object_to_string.py
tests/test_string_to_object.py
tests/test_validate.py
pyobjectid-0.1.5.dist-info/METADATA
pyobjectid-0.1.5.dist-info/WHEEL
pyobjectid-0.1.5.dist-info/top_level.txt
pyobjectid-0.1.5.dist-info/RECORD
