Metadata-Version: 2.1
Name: pyobjectid
Version: 0.1.5
Summary: A package to generate, validate, and deal with MongoDB ObjectIds.
Home-page: UNKNOWN
Author: Zifo
Author-email: ahmedshaban.sh10@Gmail.com
License: UNKNOWN
Platform: UNKNOWN
Classifier: Programming Language :: Python :: 3
Classifier: License :: OSI Approved :: MIT License
Classifier: Operating System :: OS Independent
Requires-Python: >=3.6
Requires-Dist: pydantic
Requires-Dist: pymongo
